{
  "id": 5,
  "robots": [
    {"id": "team-electronics", "name": "Team Electronics"},
    {"id": "legiones-skitarii", "name": "Legiones Skitarii"}
  ],
  "startingBaskets": ["blue", "magenta"],
  "isTieAllowed": true,
  "hasEnded": false,
  "rounds": [
    {
      "scores": [
        [
          {"time": 1702558554062, "isValid": true},
          {"time": 1702558567213, "isValid": true}
        ],
        [{"time": 1702558566610, "isValid": true}]
      ],
      "fouls": [[], []],
      "baskets": ["blue", "magenta"],
      "hasEnded": true,
      "isConfirmed": true,
      "roundMaxLength": 60000,
      "runs": [{"startTime": 1702558546464, "endTime": 1702558606556}]
    },
    {
      "scores": [
        [
          {"time": 1702558679578, "isValid": true},
          {"time": 1702558686701, "isValid": true}
        ],
        [
          {"time": 1702558682987, "isValid": true},
          {"time": 1702558687926, "isValid": true},
          {"time": 1702558695433, "isValid": true},
          {"time": 1702558702534, "isValid": true},
          {"time": 1702558713631, "isValid": false}
        ]
      ],
      "fouls": [[], []],
      "baskets": ["magenta", "blue"],
      "hasEnded": true,
      "isConfirmed": true,
      "roundMaxLength": 60000,
      "runs": [{"startTime": 1702558658652, "endTime": 1702558718750}]
    },
    {
      "scores": [
        [
          {"time": 1702558797347, "isValid": true},
          {"time": 1702558805515, "isValid": true},
          {"time": 1702558818051, "isValid": true}
        ],
        [
          {"time": 1702558791828, "isValid": true},
          {"time": 1702558800293, "isValid": true},
          {"time": 1702558810361, "isValid": true}
        ]
      ],
      "fouls": [[], []],
      "baskets": ["blue", "magenta"],
      "hasEnded": false,
      "isConfirmed": false,
      "roundMaxLength": 60000,
      "runs": [{"startTime": 1702558774655, "endTime": null}]
    }
  ],
  "ballPlacement": [
    [0, 0],
    [1.25, -0.8],
    [-1.25, 0.8],
    [1.03, 1.22],
    [-1.03, -1.22],
    [1.03, -0.69],
    [-1.03, 0.69],
    [-0.5, -0.88],
    [0.5, 0.88],
    [-0.77, 1.15],
    [0.77, -1.15]
  ]
}